{
  "name": "Evelyn Schötz",
  "party": "DIE LINKE",
  "slug": "evelyn-schoetz",
  "academicTitle": null,
  "speeches": 6,
  "wortbeitraege": 0,
  "befragungResponses": 0,
  "totalWords": 1728,
  "avgWords": 288,
  "minWords": 100,
  "maxWords": 448,
  "rankings": {
    "speechRank": 346,
    "wordsRank": 485,
    "partySpeechRank": 44,
    "partyWordsRank": 53,
    "partySize": 63,
    "totalSpeakers": 609,
    "percentile": 43.2,
    "verbosityRank": 472,
    "verbosityTotal": 521,
    "partyVerbosityRank": 51,
    "longestSpeechRank": 558
  },
  "drama": {
    "interruptionsGiven": 0,
    "interruptionsReceived": 1,
    "interrupterRank": null,
    "interruptedRank": 539
  },
  "words": {
    "topWords": [
      {
        "word": "pflege",
        "count": 20
      },
      {
        "word": "menschen",
        "count": 7
      },
      {
        "word": "pflegekräfte",
        "count": 7
      },
      {
        "word": "kosten",
        "count": 6
      },
      {
        "word": "pflegeversicherung",
        "count": 6
      },
      {
        "word": "braucht",
        "count": 6
      },
      {
        "word": "darf",
        "count": 5
      },
      {
        "word": "regierung",
        "count": 4
      },
      {
        "word": "gesetz",
        "count": 4
      },
      {
        "word": "geld",
        "count": 4
      }
    ],
    "signatureWords": [
      {
        "word": "pflegekräfte",
        "count": 7,
        "ratioParty": 150.7,
        "ratioBundestag": 123.7
      },
      {
        "word": "pflegeversicherung",
        "count": 6,
        "ratioParty": 150.7,
        "ratioBundestag": 86.1
      },
      {
        "word": "pflege",
        "count": 20,
        "ratioParty": 79.3,
        "ratioBundestag": 74.5
      },
      {
        "word": "kosten",
        "count": 6,
        "ratioParty": 7.3,
        "ratioBundestag": 9.9
      },
      {
        "word": "braucht",
        "count": 6,
        "ratioParty": 5.0,
        "ratioBundestag": 5.3
      }
    ],
    "signatureAdjectives": []
  },
  "comparison": {
    "speakerAvgWords": 288,
    "partyAvgWords": 521,
    "parliamentAvgWords": 613,
    "vsParty": 0.55,
    "vsParliament": 0.47
  },
  "funFacts": [
    {
      "emoji": "🎤",
      "label": "Reden gehalten",
      "value": "6"
    },
    {
      "emoji": "📝",
      "label": "Wörter gesprochen",
      "value": "1.728"
    }
  ],
  "signatureQuiz": {
    "question": "Welches Wort nutzt Evelyn Schötz häufiger als der Rest der Fraktion?",
    "options": [
      {
        "text": "Debatte",
        "isCorrect": false
      },
      {
        "text": "Opposition",
        "isCorrect": false
      },
      {
        "text": "Gesetzentwurf",
        "isCorrect": false
      },
      {
        "text": "Pflegekräfte",
        "isCorrect": true
      }
    ],
    "explanationParty": "\"Pflegekräfte\" nutzt Evelyn Schötz 150.7× häufiger als der DIE LINKE-Durchschnitt.",
    "explanationBundestag": "123.7× häufiger als der Bundestag-Durchschnitt."
  },
  "signatureAdjectiveQuiz": null,
  "spiritAnimal": {
    "emoji": "🦊",
    "name": "Fuchs",
    "title": "Clevere Strategin",
    "reason": "Mit eigenem Vokabular hebst du dich von der Fraktion ab.",
    "id": "fuchs",
    "alternatives": [
      {
        "emoji": "🐿️",
        "name": "Eichhörnchen",
        "title": "Themenhüterin",
        "reason": "Du hast deine Spezialthemen, die du immer wieder einbringst.",
        "id": "eichhoernchen",
        "score": 0.794
      },
      {
        "emoji": "🦫",
        "name": "Biber",
        "title": "Konstruktive Brückenbauerin",
        "reason": "Du baust Brücken zwischen Positionen – kooperativ und lösungsorientiert.",
        "id": "biber",
        "score": 0.75
      }
    ]
  },
  "toneProfile": {
    "scores": {
      "affirmative": 75.0,
      "aggression": 33.3,
      "labeling": 0.0,
      "solution_focus": 83.3,
      "collaboration": 50.0,
      "demand_intensity": 12.5,
      "acknowledgment": 12.5,
      "authority": 64.7,
      "future_orientation": 75.0,
      "emotional_intensity": 57.1,
      "inclusivity": 41.7,
      "discriminatory": 0.0
    },
    "confidence": "sufficient",
    "sampleSize": {
      "speeches": 6,
      "words": 1150,
      "adjectives": 6,
      "verbs": 8
    }
  },
  "topics": {
    "scores": {
      "migration": 0.0,
      "klima": 0.0,
      "wirtschaft": 0.87,
      "soziales": 2.61,
      "sicherheit": 0.0,
      "gesundheit": 40.87,
      "europa": 0.0,
      "digital": 0.0,
      "bildung": 1.74,
      "finanzen": 6.09,
      "justiz": 0.0,
      "arbeit": 0.87,
      "mobilitaet": 0.0
    },
    "topTopics": [
      {
        "topic": "gesundheit",
        "score": 40.87,
        "rank": 1
      },
      {
        "topic": "finanzen",
        "score": 6.09,
        "rank": 2
      },
      {
        "topic": "soziales",
        "score": 2.61,
        "rank": 3
      },
      {
        "topic": "bildung",
        "score": 1.74,
        "rank": 4
      },
      {
        "topic": "wirtschaft",
        "score": 0.87,
        "rank": 5
      }
    ],
    "topicWords": {
      "wirtschaft": [
        {
          "word": "selbstständige",
          "count": 1
        }
      ],
      "soziales": [
        {
          "word": "familien",
          "count": 1
        },
        {
          "word": "armut",
          "count": 1
        },
        {
          "word": "barrierefreiheit",
          "count": 1
        }
      ],
      "gesundheit": [
        {
          "word": "pflege",
          "count": 20
        },
        {
          "word": "pflegekräfte",
          "count": 7
        },
        {
          "word": "pflegeversicherung",
          "count": 6
        },
        {
          "word": "pflegekraft",
          "count": 3
        },
        {
          "word": "pflegegrad",
          "count": 2
        }
      ],
      "bildung": [
        {
          "word": "weiterbildung",
          "count": 1
        },
        {
          "word": "bachelor",
          "count": 1
        }
      ],
      "finanzen": [
        {
          "word": "kosten",
          "count": 6
        },
        {
          "word": "finanzierung",
          "count": 1
        }
      ],
      "arbeit": [
        {
          "word": "löhne",
          "count": 1
        }
      ]
    }
  }
}