{
  "name": "Marcel Emmerich",
  "party": "GRÜNE",
  "slug": "marcel-emmerich",
  "academicTitle": null,
  "speeches": 14,
  "wortbeitraege": 6,
  "befragungResponses": 0,
  "totalWords": 7456,
  "avgWords": 373,
  "minWords": 59,
  "maxWords": 757,
  "rankings": {
    "speechRank": 32,
    "wordsRank": 84,
    "partySpeechRank": 7,
    "partyWordsRank": 12,
    "partySize": 85,
    "totalSpeakers": 609,
    "percentile": 94.7,
    "verbosityRank": 379,
    "verbosityTotal": 521,
    "partyVerbosityRank": 45,
    "longestSpeechRank": 242
  },
  "drama": {
    "interruptionsGiven": 0,
    "interruptionsReceived": 32,
    "interrupterRank": null,
    "interruptedRank": 48
  },
  "words": {
    "topWords": [
      {
        "word": "menschen",
        "count": 17
      },
      {
        "word": "sicherheit",
        "count": 16
      },
      {
        "word": "land",
        "count": 15
      },
      {
        "word": "taliban",
        "count": 13
      }
    ],
    "signatureWords": [
      {
        "word": "rechtsbruch",
        "count": 5,
        "ratioParty": 121.2,
        "ratioBundestag": 65.8
      },
      {
        "word": "bundesinnenminister",
        "count": 8,
        "ratioParty": 77.5,
        "ratioBundestag": 27.7
      },
      {
        "word": "einsatzkräfte",
        "count": 7,
        "ratioParty": 56.5,
        "ratioBundestag": 55.7
      },
      {
        "word": "beamten",
        "count": 8,
        "ratioParty": 43.1,
        "ratioBundestag": 35.1
      },
      {
        "word": "taliban",
        "count": 13,
        "ratioParty": 35.0,
        "ratioBundestag": 53.0
      }
    ],
    "signatureAdjectives": [
      {
        "word": "verantwortungslos",
        "count": 3,
        "ratioParty": 8.6,
        "ratioBundestag": 16.8
      },
      {
        "word": "stark",
        "count": 4,
        "ratioParty": 4.2,
        "ratioBundestag": 3.4
      }
    ]
  },
  "comparison": {
    "speakerAvgWords": 373,
    "partyAvgWords": 567,
    "parliamentAvgWords": 613,
    "vsParty": 0.66,
    "vsParliament": 0.61
  },
  "funFacts": [
    {
      "emoji": "🎤",
      "label": "Reden gehalten",
      "value": "14"
    },
    {
      "emoji": "📝",
      "label": "Wörter gesprochen",
      "value": "7.456"
    },
    {
      "emoji": "📊",
      "label": "Top-Redner",
      "value": "Top 6%"
    }
  ],
  "signatureQuiz": {
    "question": "Welches Wort nutzt Marcel Emmerich häufiger als der Rest der Fraktion?",
    "options": [
      {
        "text": "Familie",
        "isCorrect": false
      },
      {
        "text": "Reform",
        "isCorrect": false
      },
      {
        "text": "Bürger",
        "isCorrect": false
      },
      {
        "text": "Rechtsbruch",
        "isCorrect": true
      }
    ],
    "explanationParty": "\"Rechtsbruch\" nutzt Marcel Emmerich 121.2× häufiger als der GRÜNE-Durchschnitt.",
    "explanationBundestag": "65.8× häufiger als der Bundestag-Durchschnitt."
  },
  "signatureAdjectiveQuiz": {
    "question": "Welches Adjektiv nutzt Marcel Emmerich häufiger als der Rest der GRÜNE-Fraktion?",
    "options": [
      {
        "text": "Verantwortungslos",
        "isCorrect": true
      },
      {
        "text": "Falsch",
        "isCorrect": false
      },
      {
        "text": "Politisch",
        "isCorrect": false
      },
      {
        "text": "Erfolgreich",
        "isCorrect": false
      }
    ],
    "explanationParty": "\"Verantwortungslos\" nutzt Marcel Emmerich 8.6× häufiger als der GRÜNE-Durchschnitt.",
    "explanationBundestag": "16.8× häufiger als der Bundestag-Durchschnitt."
  },
  "spiritAnimal": {
    "emoji": "🐿️",
    "name": "Eichhörnchen",
    "title": "Themenhüter",
    "reason": "Du hast deine Spezialthemen, die du immer wieder einbringst.",
    "id": "eichhoernchen",
    "alternatives": [
      {
        "emoji": "🐝",
        "name": "Biene",
        "title": "Fleißiger Abgeordneter",
        "reason": "Zuverlässig und engagiert – ein wichtiger Teil des Parlaments.",
        "id": "biene",
        "score": 1.0
      },
      {
        "emoji": "🐻",
        "name": "Bär",
        "title": "Standhafter Debattierer",
        "reason": "Trotz 32× unterbrochen zu werden, bleibst du standhaft.",
        "id": "baer",
        "score": 0.981
      }
    ]
  },
  "toneProfile": {
    "scores": {
      "affirmative": 72.2,
      "aggression": 34.5,
      "labeling": 3.4,
      "solution_focus": 72.1,
      "collaboration": 42.9,
      "demand_intensity": 6.9,
      "acknowledgment": 6.9,
      "authority": 81.2,
      "future_orientation": 75.4,
      "emotional_intensity": 52.2,
      "inclusivity": 47.3,
      "discriminatory": 0.21
    },
    "confidence": "sufficient",
    "sampleSize": {
      "speeches": 20,
      "words": 4859,
      "adjectives": 29,
      "verbs": 58
    }
  },
  "topics": {
    "scores": {
      "migration": 4.12,
      "klima": 0.0,
      "wirtschaft": 0.41,
      "soziales": 2.47,
      "sicherheit": 11.53,
      "gesundheit": 1.03,
      "europa": 2.68,
      "digital": 0.82,
      "bildung": 0.82,
      "finanzen": 0.82,
      "justiz": 5.76,
      "arbeit": 0.21,
      "mobilitaet": 1.23
    },
    "topTopics": [
      {
        "topic": "sicherheit",
        "score": 11.53,
        "rank": 1
      },
      {
        "topic": "justiz",
        "score": 5.76,
        "rank": 2
      },
      {
        "topic": "migration",
        "score": 4.12,
        "rank": 3
      },
      {
        "topic": "europa",
        "score": 2.68,
        "rank": 4
      },
      {
        "topic": "soziales",
        "score": 2.47,
        "rank": 5
      }
    ],
    "topicWords": {
      "migration": [
        {
          "word": "grenzkontrollen",
          "count": 3
        },
        {
          "word": "grenze",
          "count": 3
        },
        {
          "word": "asyl",
          "count": 2
        },
        {
          "word": "integration",
          "count": 2
        },
        {
          "word": "familiennachzug",
          "count": 2
        }
      ],
      "wirtschaft": [
        {
          "word": "fachkräfte",
          "count": 1
        },
        {
          "word": "unternehmen",
          "count": 1
        }
      ],
      "soziales": [
        {
          "word": "familien",
          "count": 4
        },
        {
          "word": "familie",
          "count": 3
        },
        {
          "word": "jugend",
          "count": 2
        },
        {
          "word": "kinder",
          "count": 1
        },
        {
          "word": "eltern",
          "count": 1
        }
      ],
      "sicherheit": [
        {
          "word": "waffen",
          "count": 8
        },
        {
          "word": "bundespolizei",
          "count": 7
        },
        {
          "word": "kriminalität",
          "count": 6
        },
        {
          "word": "polizisten",
          "count": 4
        },
        {
          "word": "gewalt",
          "count": 4
        }
      ],
      "gesundheit": [
        {
          "word": "prävention",
          "count": 3
        },
        {
          "word": "sucht",
          "count": 2
        }
      ],
      "europa": [
        {
          "word": "europa",
          "count": 7
        },
        {
          "word": "außenminister",
          "count": 2
        },
        {
          "word": "außenpolitik",
          "count": 1
        },
        {
          "word": "putin",
          "count": 1
        },
        {
          "word": "europäisch",
          "count": 1
        }
      ],
      "digital": [
        {
          "word": "daten",
          "count": 3
        },
        {
          "word": "cybersicherheit",
          "count": 1
        }
      ],
      "bildung": [
        {
          "word": "ausbildung",
          "count": 2
        },
        {
          "word": "wissenschaft",
          "count": 1
        },
        {
          "word": "fortbildung",
          "count": 1
        }
      ],
      "finanzen": [
        {
          "word": "schuldenbremse",
          "count": 1
        },
        {
          "word": "haushalt",
          "count": 1
        },
        {
          "word": "kosten",
          "count": 1
        },
        {
          "word": "banken",
          "count": 1
        }
      ],
      "justiz": [
        {
          "word": "rechtsstaat",
          "count": 4
        },
        {
          "word": "gerichte",
          "count": 4
        },
        {
          "word": "rechtsstaatlichkeit",
          "count": 3
        },
        {
          "word": "menschenrechte",
          "count": 3
        },
        {
          "word": "gericht",
          "count": 3
        }
      ],
      "arbeit": [
        {
          "word": "gehalt",
          "count": 1
        }
      ],
      "mobilitaet": [
        {
          "word": "auto",
          "count": 2
        },
        {
          "word": "stau",
          "count": 2
        },
        {
          "word": "infrastruktur",
          "count": 1
        },
        {
          "word": "straße",
          "count": 1
        }
      ]
    }
  }
}